Workbook

Sheet Program Summary
A1: AI Program Change Management - Overall Progress
A2: Percent complete is the average of the % Complete column on the Project Plan tab. Figures update automatically as that tab is maintained.
A4: Scope | B4: Tasks | C4: % Complete | D4: Complete | E4: In Progress | F4: Not Started / Deferred
A5: Entire program | B5: =COUNTA('Project Plan'!$B$2:$B$500) -> 164 | C5: =AVERAGE('Project Plan'!$H$2:$H$500) -> 0.27835366 | D5: =COUNTIF('Project Plan'!$G$2:$G$500,"Complete") -> 29 | E5: =COUNTIF('Project Plan'!$G$2:$G$500,"In Progress") -> 35 | F5: =COUNTIF('Project Plan'!$G$2:$G$500,"Not Started")+COUNTIF('Project Plan'!$G$2:$G$500,"Deferred") -> 100
A7: By track and phase
A8: Scope | B8: Tasks | C8: % Complete | D8: Complete | E8: In Progress | F8: Not Started / Deferred
A9: Copilot Basic | Phase 0 - Readiness (through 9/11) | B9: =COUNTIF('Project Plan'!$B$2:$B$500,"Copilot Basic | Phase 0 - Readiness (through 9/11)") -> 62 | C9: =IFERROR(AVERAGEIF('Project Plan'!$B$2:$B$500,"Copilot Basic | Phase 0 - Readiness (through 9/11)",'Project Plan'!$H$2:$H$500),0) -> 0.55483871 | D9: =COUNTIFS('Project Plan'!$B$2:$B$500,"Copilot Basic | Phase 0 - Readiness (through 9/11)",'Project Plan'!$G$2:$G$500,"Complete") -> 21 | E9: =COUNTIFS('Project Plan'!$B$2:$B$500,"Copilot Basic | Phase 0 - Readiness (through 9/11)",'Project Plan'!$G$2:$G$500,"In Progress") -> 25 | F9: =COUNTIFS('Project Plan'!$B$2:$B$500,"Copilot Basic | Phase 0 - Readiness (through 9/11)",'Project Plan'!$G$2:$G$500,"Not Started")+COUNTIFS('Project Plan'!$B$2:$B$500,"Copilot Basic | Phase 0 - Readiness (through 9/11)",'Project Plan'!$G$2:$G$500,"Deferred") -> 16
A10: Copilot Basic | Phase 1 - Rolling Training Delivery (9/21/26 onward; see Training Capacity Plan tab) | B10: =COUNTIF('Project Plan'!$B$2:$B$500,"Copilot Basic | Phase 1 - Rolling Training Delivery (9/21/26 onward; see Training Capacity Plan tab)") -> 32 | C10: =IFERROR(AVERAGEIF('Project Plan'!$B$2:$B$500,"Copilot Basic | Phase 1 - Rolling Training Delivery (9/21/26 onward; see Training Capacity Plan tab)",'Project Plan'!$H$2:$H$500),0) -> 0.090625 | D10: =COUNTIFS('Project Plan'!$B$2:$B$500,"Copilot Basic | Phase 1 - Rolling Training Delivery (9/21/26 onward; see Training Capacity Plan tab)",'Project Plan'!$G$2:$G$500,"Complete") -> 1 | E10: =COUNTIFS('Project Plan'!$B$2:$B$500,"Copilot Basic | Phase 1 - Rolling Training Delivery (9/21/26 onward; see Training Capacity Plan tab)",'Project Plan'!$G$2:$G$500,"In Progress") -> 4 | F10: =COUNTIFS('Project Plan'!$B$2:$B$500,"Copilot Basic | Phase 1 - Rolling Training Delivery (9/21/26 onward; see Training Capacity Plan tab)",'Project Plan'!$G$2:$G$500,"Not Started")+COUNTIFS('Project Plan'!$B$2:$B$500,"Copilot Basic | Phase 1 - Rolling Training Delivery (9/21/26 onward; see Training Capacity Plan tab)",'Project Plan'!$G$2:$G$500,"Deferred") -> 27
A11: Copilot Basic | Phase 2 - Monitoring & Continuous Improvement (ongoing) | B11: =COUNTIF('Project Plan'!$B$2:$B$500,"Copilot Basic | Phase 2 - Monitoring & Continuous Improvement (ongoing)") -> 26 | C11: =IFERROR(AVERAGEIF('Project Plan'!$B$2:$B$500,"Copilot Basic | Phase 2 - Monitoring & Continuous Improvement (ongoing)",'Project Plan'!$H$2:$H$500),0) -> 0 | D11: =COUNTIFS('Project Plan'!$B$2:$B$500,"Copilot Basic | Phase 2 - Monitoring & Continuous Improvement (ongoing)",'Project Plan'!$G$2:$G$500,"Complete") -> 0 | E11: =COUNTIFS('Project Plan'!$B$2:$B$500,"Copilot Basic | Phase 2 - Monitoring & Continuous Improvement (ongoing)",'Project Plan'!$G$2:$G$500,"In Progress") -> 0 | F11: =COUNTIFS('Project Plan'!$B$2:$B$500,"Copilot Basic | Phase 2 - Monitoring & Continuous Improvement (ongoing)",'Project Plan'!$G$2:$G$500,"Not Started")+COUNTIFS('Project Plan'!$B$2:$B$500,"Copilot Basic | Phase 2 - Monitoring & Continuous Improvement (ongoing)",'Project Plan'!$G$2:$G$500,"Deferred") -> 26
A12: HR Chatbot | Readiness & Provisioning (through 10/2) | B12: =COUNTIF('Project Plan'!$B$2:$B$500,"HR Chatbot | Readiness & Provisioning (through 10/2)") -> 21 | C12: =IFERROR(AVERAGEIF('Project Plan'!$B$2:$B$500,"HR Chatbot | Readiness & Provisioning (through 10/2)",'Project Plan'!$H$2:$H$500),0) -> 0.39761905 | D12: =COUNTIFS('Project Plan'!$B$2:$B$500,"HR Chatbot | Readiness & Provisioning (through 10/2)",'Project Plan'!$G$2:$G$500,"Complete") -> 7 | E12: =COUNTIFS('Project Plan'!$B$2:$B$500,"HR Chatbot | Readiness & Provisioning (through 10/2)",'Project Plan'!$G$2:$G$500,"In Progress") -> 6 | F12: =COUNTIFS('Project Plan'!$B$2:$B$500,"HR Chatbot | Readiness & Provisioning (through 10/2)",'Project Plan'!$G$2:$G$500,"Not Started")+COUNTIFS('Project Plan'!$B$2:$B$500,"HR Chatbot | Readiness & Provisioning (through 10/2)",'Project Plan'!$G$2:$G$500,"Deferred") -> 8
A13: HR Chatbot | Three-Phase Testing (10/5-11/20) | B13: =COUNTIF('Project Plan'!$B$2:$B$500,"HR Chatbot | Three-Phase Testing (10/5-11/20)") -> 14 | C13: =IFERROR(AVERAGEIF('Project Plan'!$B$2:$B$500,"HR Chatbot | Three-Phase Testing (10/5-11/20)",'Project Plan'!$H$2:$H$500),0) -> 0 | D13: =COUNTIFS('Project Plan'!$B$2:$B$500,"HR Chatbot | Three-Phase Testing (10/5-11/20)",'Project Plan'!$G$2:$G$500,"Complete") -> 0 | E13: =COUNTIFS('Project Plan'!$B$2:$B$500,"HR Chatbot | Three-Phase Testing (10/5-11/20)",'Project Plan'!$G$2:$G$500,"In Progress") -> 0 | F13: =COUNTIFS('Project Plan'!$B$2:$B$500,"HR Chatbot | Three-Phase Testing (10/5-11/20)",'Project Plan'!$G$2:$G$500,"Not Started")+COUNTIFS('Project Plan'!$B$2:$B$500,"HR Chatbot | Three-Phase Testing (10/5-11/20)",'Project Plan'!$G$2:$G$500,"Deferred") -> 14
A14: HR Chatbot | ESC Approval & Pilot (11/30 onward) | B14: =COUNTIF('Project Plan'!$B$2:$B$500,"HR Chatbot | ESC Approval & Pilot (11/30 onward)") -> 9 | C14: =IFERROR(AVERAGEIF('Project Plan'!$B$2:$B$500,"HR Chatbot | ESC Approval & Pilot (11/30 onward)",'Project Plan'!$H$2:$H$500),0) -> 0 | D14: =COUNTIFS('Project Plan'!$B$2:$B$500,"HR Chatbot | ESC Approval & Pilot (11/30 onward)",'Project Plan'!$G$2:$G$500,"Complete") -> 0 | E14: =COUNTIFS('Project Plan'!$B$2:$B$500,"HR Chatbot | ESC Approval & Pilot (11/30 onward)",'Project Plan'!$G$2:$G$500,"In Progress") -> 0 | F14: =COUNTIFS('Project Plan'!$B$2:$B$500,"HR Chatbot | ESC Approval & Pilot (11/30 onward)",'Project Plan'!$G$2:$G$500,"Not Started")+COUNTIFS('Project Plan'!$B$2:$B$500,"HR Chatbot | ESC Approval & Pilot (11/30 onward)",'Project Plan'!$G$2:$G$500,"Deferred") -> 9
A16: By track
A17: Scope | B17: Tasks | C17: % Complete | D17: Complete | E17: In Progress | F17: Not Started / Deferred
A18: Copilot Basic | B18: =COUNTIF('Project Plan'!$B$2:$B$500,"Copilot Basic*") -> 120 | C18: =IFERROR(AVERAGEIF('Project Plan'!$B$2:$B$500,"Copilot Basic*",'Project Plan'!$H$2:$H$500),0) -> 0.31083333 | D18: =COUNTIFS('Project Plan'!$B$2:$B$500,"Copilot Basic*",'Project Plan'!$G$2:$G$500,"Complete") -> 22 | E18: =COUNTIFS('Project Plan'!$B$2:$B$500,"Copilot Basic*",'Project Plan'!$G$2:$G$500,"In Progress") -> 29 | F18: =COUNTIFS('Project Plan'!$B$2:$B$500,"Copilot Basic*",'Project Plan'!$G$2:$G$500,"Not Started")+COUNTIFS('Project Plan'!$B$2:$B$500,"Copilot Basic*",'Project Plan'!$G$2:$G$500,"Deferred") -> 69
A19: HR Chatbot | B19: =COUNTIF('Project Plan'!$B$2:$B$500,"HR Chatbot*") -> 44 | C19: =IFERROR(AVERAGEIF('Project Plan'!$B$2:$B$500,"HR Chatbot*",'Project Plan'!$H$2:$H$500),0) -> 0.18977273 | D19: =COUNTIFS('Project Plan'!$B$2:$B$500,"HR Chatbot*",'Project Plan'!$G$2:$G$500,"Complete") -> 7 | E19: =COUNTIFS('Project Plan'!$B$2:$B$500,"HR Chatbot*",'Project Plan'!$G$2:$G$500,"In Progress") -> 6 | F19: =COUNTIFS('Project Plan'!$B$2:$B$500,"HR Chatbot*",'Project Plan'!$G$2:$G$500,"Not Started")+COUNTIFS('Project Plan'!$B$2:$B$500,"HR Chatbot*",'Project Plan'!$G$2:$G$500,"Deferred") -> 31

Sheet Training Capacity Plan
A1: License Breakdown
A2: Department | B2: E5 Licenses Assigned (laptop) | C2: F3 Licenses Assigned (field, no laptop) | D2: Total
A3: General Fund (GF) | B3: 4041 | C3: 1236 | D3: =B3+C3 -> 5277
A4: Utilities (DPU) | B4: 1240 | C4: 340 | D4: =B4+C4 -> 1580
A5: Airports (DPC) | B5: 325 | C5: 225 | D5: =B5+C5 -> 550
A6: Total | B6: =SUM(B3:B5) -> 5606 | C6: =SUM(C3:C5) -> 1801 | D6: =SUM(D3:D5) -> 7407
A7: E5 = standard laptop-equipped users. F3 = field/frontline users with tool access but no assigned laptop - delivery format (in-person kiosk/shared device, mobile-friendly session, or alternate scheduling) needs to account for this group separately from a standard classroom/virtual session.
A8: Delivery Track Assumptions
A9: Track | B9: Format | C9: Employees | D9: Capacity per Session | E9: Cadence (sessions/week) | F9: Sessions Needed | G9: Weeks Needed
A10: E5 (Laptop) | B10: Virtual | C10: =B6 -> 5606 | D10: No limit (Microsoft) | E10: 3 | F10: 6 | G10: =ROUNDUP(F10/E10,0) -> 2
A11: F3 (Field) - Out of Scope (Phase 1) | B11: In-Person (Room) | C11: =C6 -> 1801 | D11: 40 | E11: 2 | F11: =ROUNDUP(C11/D11,0) -> 46 | G11: =ROUNDUP(F11/E11,0) -> 23
A12: This phase focuses on E5 (laptop-equipped) employees only - F3 (field, no-laptop) employees are out of scope for now and will be addressed in a later phase. Microsoft places no attendance limit on virtual Teams sessions, so E5 capacity is not a constraint; the six sessions are a scheduling decision that repeats the same curriculum for coverage, not a capacity calculation. No registration is required - attendance is captured from the Microsoft Teams attendance report at join. F3 row retained below for reference only and is excluded from the Weeks Needed calculation.
A13: Shaded cells are entered values. Unshaded bold cells are calculated.
A14: Assumption | B14: Value | C14: Notes
A15: Rollout start date (first live session) | B15: 46335 | C15: First live session of the six-session Microsoft curriculum, following the 10/28/26 citywide launch and the 10/30 launch communication. 11/2-11/6 is a deliberate self-guided familiarization week ahead of instruction.
A16: Weeks needed (E5 only) | B16: =G10 -> 2 | C16: E5 (laptop) track only. Six sessions delivered at three per week over two weeks (11/9-11/20), compressed to wrap ahead of Thanksgiving per Renee Raffalli's direction. F3 (field) is out of scope for this phase.
A17: Estimated rollout end date | B17: =B15+(B16*7)-1 -> 46348 | C17: Start date plus (weeks needed x 7 days). Calculated end 11/22/26; the scheduled final session is Friday 11/20/26.
A18: Estimated duration (months) | B18: =ROUND((B17-B15)/30.4,1) -> 0.4 | C18: Compressed two-week delivery replaces the earlier multi-month assumption, per the Rollout Plan v1.9 schedule approved for ESC presentation.

Sheet Project Team
A1: Resource | B1: Team | C1: Area
A2: Atri Manthani | B2: AI | C2: Technical Development, Strategy, Monitoring & Continuous Improvement
A3: Brad Beran (Microsoft) | B3: Microsoft | C3: Copilot Basic training workshops and session scheduling
A4: Brian Umerley | B4: Innovations & Process Improvement | C4: Backup to Tawanna for attendance coordination and the access and training tracker; training session support. Capacity not yet confirmed, so no line is solely dependent on him.
A5: Chief Crowe | B5: Chief, ITS | C5: Stakeholder
A6: Commissioner Larry Jones | B6: Commissioner, ITS | C6: Stakeholder
A7: Cora Harmon | B7: Innovations & Process Improvement | C7: Communication Roadmap Template
A8: Daisha Olmeda | B8: Innovations & Process Improvement | C8: Provide Resources from Innovations & Process Improvement Team
A9: DC Faranak Arab | B9: ITS - O365 Global Administration | C9: Tenant configuration, license assignment and reclamation by authorized phase
A10: DC Jesse Frye | B10: ITS | C10: Source for the master user list across General Fund, Utilities (DPU) and Airports (DPC)
A11: Doug Meil | B11: Data Engineering | C11: Leading the AI Policies creation, documentation, approvals
A12: Dustin Hargis | B12: Human Resources | C12: HR business lead; Phase 2 tester and Phase 3 Generalist roster owner
... A22: TBD | B22: Data Engineering | C22: Build the workflows for data monitoring

Sheet Project Plan
A1: # | B1: Phase | C1: Type | D1: Task / Deliverable | E1: Owner | F1: Due Date | G1: Status | H1: % Complete | I1: Notes / Details | J1: Comms Phase
A2: 1 | B2: Copilot Basic | Phase 0 - Readiness (through 9/11) | C2: Note | D2: Note: current monitoring tooling scope is G5-license dependent (other tiers TBD) | E2: AI CoE | F2: 46258 | G2: Complete | H2: 1 | I2: The monitoring and governance tooling outlined in this plan currently applies to Microsoft 365 G5-licensed users. Extending equivalent coverage to other license tiers will be evaluated and defined (TBD) as licensing scope and platform capabilities evolve. | J2: n/a - not a comms task
A3: 2 | B3: Copilot Basic | Phase 0 - Readiness (through 9/11) | C3: Task | D3: Design training curriculum | E3: Atri Manthani, AI CoE | F3: 46255 | G3: Complete | H3: 1 | I3: Sent to Renee Raffalli and Doug | J3: n/a - not a comms task
A4: 3 | B4: Copilot Basic | Phase 0 - Readiness (through 9/11) | C4: Note | D4: Note: all employees already have Copilot access via Entra ID | E4: AI CoE, ITS | F4: 46259 | G4: Complete | H4: 1 | I4: Access is provisioned; employees do not yet have the Copilot Basic link and web grounding is currently off - see Turn on web grounding and Launch Date tasks | J4: n/a - not a comms task
A5: 4 | B5: Copilot Basic | Phase 0 - Readiness (through 9/11) | C5: Milestone | D5: Analytics & dashboard readiness gate | E5: Tawanna Armstrong-Ivory, Atri Manthani, Innovations Team (Daisha) | F5: 46258 | G5: In Progress | H5: 0.1 | I5: Analytics Monitoring Plan, Communications Plan, locked metrics, and Dashboard access all due | J5: n/a - not a comms task
A6: 5 | B6: Copilot Basic | Phase 0 - Readiness (through 9/11) | C6: Task | D6: Turn on web grounding | E6: DC Faranak | F6: 46276 | G6: Complete | H6: 1 | I6: Provide the communication plan and dates to DC Faranak so that web grounding can be enabled within the tenant. Call scheduled with DC Faranak for 8/31 to discuss enabling web grounding for the Copilot Basic launch; 8/31 met with DC Faranak and she will work to enable; 9/2 tested with some users in IT and UAI and getting the message that web grounding isn't enabled; sent email reminder to DC Faranak; 9/8 sent email reminder; 9/15 - Web grounding was enabled today with DC Faranak and Microsoft (call). | J6: n/a - not a comms task
A7: 6 | B7: Copilot Basic | Phase 0 - Readiness (through 9/11) | C7: Task | D7: Plan for Analytics Monitoring Plan DRAFT | E7: Atri Manthani | F7: 46258 | G7: Complete | H7: 1 | I7: Draft due 8/24 per Summary Timeline; Atri sent on 8/21, Tawanna added the monitoring docs to the Monitoring folder. Covers: where analytics come from, who is responsible for monitoring, what is being monitored, which analytics are shared out, and how often analytics are shared | J7: n/a - not a comms task
A8: 7 | B8: Copilot Basic | Phase 0 - Readiness (through 9/11) | C8: Task | D8: Plan for Communications Plan DRAFT | E8: Tawanna Armstrong-Ivory, Atri Manthani, Innovations Team (Daisha and Cora) | F8: 46258 | G8: Complete | H8: 1 | I8: Draft due 8/24 per Summary Timeline; Tawanna sent email to Renee Raffalli on 8/21; Cora provided the Copilot Basic Communication Roadmap to the Communications Folder | J8: 1 - Awareness
A9: 8 | B9: Copilot Basic | Phase 0 - Readiness (through 9/11) | C9: Task | D9: Plan for Building Hub resource page | E9: Tawanna Armstrong-Ivory, Innovations Team (Meg/Vikki) | F9: 46289 | G9: In Progress | H9: 0.25 | I9: Persistent single source of truth: FAQs, links, status, Office Hours/Champion Channel links; in progress (info gathering) - provided basic Copilot info, working to get additional materials. Received AI Hub link (Hub Resource Page) from DC Faranak on 8/25; looped in Vikki/Megan. 8/25 Atri provided content for the hub to Megan. | J9: 1 - Awareness
A10: 9 | B10: Copilot Basic | Phase 0 - Readiness (through 9/11) | C10: Task | D10: Prepare Cabinet presentation | E10: Tawanna Armstrong-Ivory, Innovations Team (Daisha, Vikki), Renee Raffalli | F10: 46276 | G10: In Progress | H10: 0.25 | I10: Covers why now, governance alignment (NIST AI RMF), and the revised multi-month session schedule; work with Innovations team on content | J10: 1 - Awareness
A11: 10 | B11: Copilot Basic | Phase 0 - Readiness (through 9/11) | C11: Task | D11: Prepare Chiefs & Directors email | E11: Tawanna Armstrong-Ivory, Innovations Team (Daisha), Renee Raffalli | F11: 46276 | G11: In Progress | H11: 0.25 | I11: One-time at launch; summarizes scope and the rolling session schedule; re-referenced at each milestone; work with Innovations team on content | J11: 1 - Awareness
A12: 11 | B12: Copilot Basic | Phase 0 - Readiness (through 9/11) | C12: Task | D12: Prepare comms email blast template (ahead of each session) | E12: Tawanna Armstrong-Ivory, Innovations Team (Daisha), Renee Raffalli, Brian Umerley | F12: 46276 | G12: In Progress | H12: 0.25 | I12: Includes registration link and seats-remaining status; reused ahead of every scheduled session. Template must carry the pre-training pulse survey link and the standing note that the post-session survey is issued at session close. Brian Umerley sends the invitation ahead of each session using this approved template. | J12: 3 - Readiness
A13: 12 | B13: Copilot Basic | Phase 0 - Readiness (through 9/11) | C13: Task | D13: Prepare AppSpace digital-signage graphic | E13: Tawanna Armstrong-Ivory, Innovations Team (Vikki) | F13: 46276 | G13: In Progress | H13: 0.25 | I13: In progress (info gathering) - provided basic Copilot info, working to get additional materials | J13: 3 - Readiness
... A21: 20 | B21: Copilot Basic | Phase 0 - Readiness (through 9/11) | C21: Task | D21: Finalize & submit Roll Out Plan sized to ~5,606 E5 employees | E21: Tawanna Armstrong-Ivory, Renee Raffalli | F21: 46262 | G21: Complete | H21: 1 | I21: This phase focuses on E5 (laptop) employees only; F3 (field, ~1,801) is out of scope for now. Open-enrollment format across a rolling multi-session schedule (see Training Capacity Plan tab); confirm actual platform capacity and facilitator availability. Timeline update: original target was all staff with access and training offered by 10/31/26 - access (link/getting-started) is on track for the 10/31 launch, but live training now runs 11/9-12/6 under the post-launch curriculum; utilizes Microsoft Teams under the Unified Contract for delivery | J21: 3 - Readiness
A22: 21 | B22: Copilot Basic | Phase 0 - Readiness (through 9/11) | C22: Task | D22: Design delivery approach for F3 (field, no-laptop) employees separately from E5 (laptop) employees | E22: Tawanna Armstrong-Ivory, Atri Manthani, Innovations Team (Daisha) | G22: Deferred | H22: 1 | I22: 1,801 F3 licenses across GF/DPU/DPC (per license breakdown on Training Capacity Plan tab); out of scope for this phase, which focuses on E5 only - revisit in a later phase The BizLibrary recording may also serve the F3 track when it is picked back up. | J22: n/a - not a comms task
A23: 22 | B23: Copilot Basic | Phase 0 - Readiness (through 9/11) | C23: Task | D23: Finalize sign-up/attendance method for E5 virtual sessions | E23: Tawanna Armstrong-Ivory, Atri Manthani, Innovations Team (Daisha, Brian Umerley) | F23: 46262 | G23: Complete | H23: 1 | I23: Microsoft places no attendance cap on E5 virtual sessions - decide whether to still require registration or rely on Microsoft's post-session attendee export instead (see Open Decisions). F3 registration/waitlist approach deferred with the F3 track. We will send out the link with our comms plan, so registration will not be needed. We will track those user who have participated in training for adoption purposes.; 9/8 - per Renee Rafalli, Brian Umerley will take the lead on sending out the invites and tracking participants.. Format confirmed as Webinar in Teams, selected for capacity; employees are not required to register. | J23: 3 - Readiness
A24: 23 | B24: Copilot Basic | Phase 0 - Readiness (through 9/11) | C24: Milestone | D24: Reinforcement infrastructure in place gate | E24: Tawanna Armstrong-Ivory, Atri Manthani, Innovations Team (Daisha) | F24: 46269 | G24: Complete | H24: 1 | I24: Surveys, compliance monitoring, and reinforcement activities all due | J24: n/a - not a comms task
A25: 24 | B25: Copilot Basic | Phase 0 - Readiness (through 9/11) | C25: Task | D25: Design pre-training pulse survey | E25: Tawanna Armstrong-Ivory, Atri Manthani, Innovations Team (Daisha, Vikki) | F25: 46269 | G25: Complete | H25: 1 | I25: Microsoft Forms/Viva; baseline AI familiarity, current public/shadow AI tool use, confidence level; 8/27 - Created and ready for review. v1.4 anonymous instrument, 11 questions: session date, baseline familiarity, prior Copilot surface use, current AI tool frequency, top weekly tasks, task to hand off, prompt-writing confidence (1-5), biggest concern, awareness of acceptable-use guidance, success criteria, preferred learning format. Surface list limited to in-scope apps only - Word, Excel and PowerPoint (app or web) plus Copilot Chat; Outlook and Teams removed since Copilot Basic does not surface there. Q2, Q3, Q7 and Q9 are repeated verbatim on the post and 90-day instruments and must not be reworded. | J25: 3 - Readiness
A26: 25 | B26: Copilot Basic | Phase 0 - Readiness (through 9/11) | C26: Task | D26: Design post-training pulse survey | E26: Tawanna Armstrong-Ivory, Atri Manthani, Innovations Team (Daisha, Vikki) | F26: 46269 | G26: Complete | H26: 1 | I26: Microsoft Forms/Viva; confidence change, perceived usefulness, intent-to-use, biggest-blocker question; 8/27 - Created and ready for review. v1.4 anonymous instrument, 12 questions. Q2-Q4 repeat pre-training Q7, Q2 and Q9 verbatim for aggregate lift; remainder covers session quality, pace, most useful segment, planned use case, 5-day intent-to-use, remaining blocker, follow-up topics, and NPS. Q9 and Q10 are repeated on the 30-day mini-pulse. | J26: 3 - Readiness
A27: 26 | B27: Copilot Basic | Phase 0 - Readiness (through 9/11) | C27: Task | D27: Schedule 90-day follow-up survey | E27: Tawanna Armstrong-Ivory, Innovations Team (Daisha, Vikki) | F27: 46269 | G27: Complete | H27: 1 | I27: Tied to the Great Copilot Journey cadence; realized usage vs. intended usage; 8/27 - Created and ready for review. v1.4 anonymous instrument, 12 questions measuring actual behavior rather than intent: 30-day usage frequency, surfaces actually used, repeated confidence item, time saved per week, work-quality change, drop-off diagnosis, unclear-permission incidents, peer teaching, biggest unlock, and demand for an intermediate session. Surface list matches the pre-training instrument (in-scope apps only). Fields 90 days after the final session (target 2/18/27); interim 30-day mini-pulse tracked separately under Phase 2. | J27: 3 - Readiness
A28: 27 | B28: Copilot Basic | Phase 0 - Readiness (through 9/11) | C28: Task | D28: Confirm eDiscovery access restricted to Legal/Compliance | E28: Security (Rajan Sharma and Peter Rodenberg)/Legal/Compliance | F28: 46269 | G28: Deferred | H28: 1 | I28: Content-level (actual prompt/response text) review reserved for legal holds and formal investigations only - not a standing dashboard | J28: n/a - not a comms task
A29: 28 | B29: Copilot Basic | Phase 0 - Readiness (through 9/11) | C29: Task | D29: Schedule reinforcement activities (Prompt-a-thon, Great Copilot Journey) | E29: Tawanna Armstrong-Ivory, Atri Manthani, Microsoft | F29: 46269 | G29: In Progress | H29: 0.75 | I29: Need to confirm workshop dates with Microsoft (Brad Beran); 9/10 we confirmed the dates and provided those to Brian and ESC. Brian is working to add those to the calendar via Teams Webinar. | J29: 5 - Sustainment
A30: 29 | B30: Copilot Basic | Phase 0 - Readiness (through 9/11) | C30: Task | D30: Confirm HIPAA BAA and CJIS Security Addendum status | E30: Tawanna Armstrong-Ivory, IT Security (Rajan Sharma, Peter Rodenberg) | F30: 46276 | G30: Deferred | H30: 1 | I30: Hard gate - required before any regulated-data content is included.; 9/8 - sent email to Rajan to determine if this is needed; 9/10 - confirmed this is not needed. The data doesn't leave the tenant nor become public. 9/14 -Met with Peter and Rajan, confirmed we are good to go. Peter will be adding overarching policies, but that shouldn't impact what we currently have enabled. | J30: n/a - not a comms task
A31: 30 | B31: Copilot Basic | Phase 0 - Readiness (through 9/11) | C31: Task | D31: Draft Leadership Announcement message (why now, strategic vision) | E31: Tawanna Armstrong-Ivory, Atri Manthani, Renee Raffalli; Innovations Team (Vikki) | F31: 46281 | G31: In Progress | H31: 0.5 | I31: Per Comms Roadmap Phase 1 - Awareness; high-level message from executive leadership introducing the change | J31: 1 - Awareness
A32: 31 | B32: Copilot Basic | Phase 0 - Readiness (through 9/11) | C32: Task | D32: Publish High-Level Overview Document and initial FAQ sheet - Infor for Hub | E32: Tawanna Armstrong-Ivory, Atri Manthani, Innovations Team (Vikki Pickett and Meg) | F32: 46281 | G32: In Progress | H32: 0.5 | I32: Per Comms Roadmap Phase 1 - Awareness; one-page 'What is Copilot' overview plus FAQ focused on high-level concerns | J32: 1 - Awareness
A33: 32 | B33: Copilot Basic | Phase 0 - Readiness (through 9/11) | C33: Task | D33: Produce awareness/countdown signage (digital and physical) | E33: Innovations Team (Vikki Pickett) | F33: 46281 | G33: In Progress | H33: 0.5 | I33: Per Comms Roadmap Phase 1 - Awareness; highlights countdown to launch date | J33: 1 - Awareness
A34: 33 | B34: Copilot Basic | Phase 0 - Readiness (through 9/11) | C34: Task | D34: Build Process Guide (terminology, definitions, interface navigation) | E34: Tawanna Armstrong-Ivory, Atri Manthani, Innovations Team (Vikki Pickett) | F34: 46281 | G34: In Progress | H34: 0.5 | I34: Per Comms Roadmap Phase 2 - Understanding; visual breakdown of key terms and navigation | J34: 2 - Understanding
... A65: 64 | B65: Copilot Basic | Phase 1 - Rolling Training Delivery (9/21/26 onward; see Training Capacity Plan tab) | C65: Task | D65: Stand up live FAQ and Known Issues document for day-1 issues | E65: AI CoE, Innovations Team (Vikki - Hub) | F65: 46323 | G65: Not Started | H65: 0 | I65: Per Comms Roadmap Phase 4 - Action and Go-Live; hosted on the Hub, updated in real time. Re-dated 9/15/26 to align with ESC deck v1.24. Previously 09/21/26. | J65: 4 - Action & Go-Live
A66: 65 | B66: Copilot Basic | Phase 1 - Rolling Training Delivery (9/21/26 onward; see Training Capacity Plan tab) | C66: Task | D66: Deliver unified curriculum at each scheduled session | E66: AI CoE / Microsoft | G66: Not Started | H66: 0 | I66: Same content, order, and depth at every session across the full rollout - not split or shortened as the series continues | J66: 4 - Action & Go-Live
A67: 66 | B67: Copilot Basic | Phase 1 - Rolling Training Delivery (9/21/26 onward; see Training Capacity Plan tab) | C67: Task | D67: Schedule dedicated sessions/timeslots for F3 field employees | E67: AI CoE, Innovations Team (Daisha) | G67: Deferred | H67: 1 | I67: Out of scope for this phase, which focuses on E5 only - revisit in a later phase | J67: n/a - not a comms task
A68: 67 | B68: Copilot Basic | Phase 1 - Rolling Training Delivery (9/21/26 onward; see Training Capacity Plan tab) | C68: Task | D68: Distribute Quick Reference slide and Official Training Manual at each session | E68: AI CoE, Innovations Team (Vikki - Hub) | G68: Not Started | H68: 0 | I68: Given at the close of every session | J68: 4 - Action & Go-Live
A69: 68 | B69: Copilot Basic | Phase 1 - Rolling Training Delivery (9/21/26 onward; see Training Capacity Plan tab) | C69: Task | D69: Enroll each session's attendees in Copilot Academy self-paced modules | E69: AI CoE, Innovations Team (Vikki - Hub) | G69: Not Started | H69: 0 | I69: Referenced at close of every session for employees who want to go beyond the baseline curriculum | J69: 4 - Action & Go-Live
A70: 69 | B70: Copilot Basic | Phase 1 - Rolling Training Delivery (9/21/26 onward; see Training Capacity Plan tab) | C70: Task | D70: Track registration/attendance against the 5,606 E5-employee target; adjust cadence if behind pace | E70: Tawanna Armstrong-Ivory, Microsoft, Innovations Team (Vikki - Hub), Brian Umerley | G70: Not Started | H70: 0 | I70: Compare actuals to the Training Capacity Plan tab. Brian Umerley exports the Microsoft Teams attendance report the same day as each session and stores it centrally; that export is the only attendance record and the adoption roster. Brian maintains a running cumulative count against the 5,606 E5 target. F3 (~1,801) out of scope for this phase. | J70: n/a - not a comms task
A71: 70 | B71: Copilot Basic | Phase 1 - Rolling Training Delivery (9/21/26 onward; see Training Capacity Plan tab) | C71: Task | D71: Recruit and grow Champion Network volunteers across sessions | E71: AI CoE | G71: Not Started | H71: 0 | I71: Ongoing recruitment as each new cohort completes training | J71: 5 - Sustainment
A72: 71 | B72: Copilot Basic | Phase 1 - Rolling Training Delivery (9/21/26 onward; see Training Capacity Plan tab) | C72: Task | D72: Open and maintain Champion Channel | E72: AI CoE, Innovations Team (Vikki - Hub) | F72: 46323 | G72: Not Started | H72: 0 | I72: Opens after the first session; stays open through the rollout and beyond. Re-dated 9/15/26 to align with ESC deck v1.24. Previously 09/21/26. | J72: 5 - Sustainment
A73: 72 | B73: Copilot Basic | Phase 1 - Rolling Training Delivery (9/21/26 onward; see Training Capacity Plan tab) | C73: Task | D73: Post-session logistics retrospective after each session | E73: Tawanna Armstrong-Ivory | G73: Not Started | H73: 0 | I73: Curriculum content stays fixed; only logistics (registration flow, pacing, room/platform setup) are refined between sessions | J73: n/a - not a comms task
A74: 73 | B74: Copilot Basic | Phase 1 - Rolling Training Delivery (9/21/26 onward; see Training Capacity Plan tab) | C74: Milestone | D74: Rollout midpoint checkpoint - confirm pace against 5,606 E5-employee target | E74: Tawanna Armstrong-Ivory, Brian Umerley | F74: 46339 | G74: Not Started | H74: 0 | I74: Brian Umerley provides the cumulative trained-to-date count against the 5,606 E5 target for the 11/13 checkpoint. Report to ESC/Cabinet; escalate if pace requires added sessions in the second week. | J74: n/a - not a comms task
A75: 74 | B75: Copilot Basic | Phase 1 - Rolling Training Delivery (9/21/26 onward; see Training Capacity Plan tab) | C75: Milestone | D75: All scheduled sessions complete / citywide training target met | E75: Tawanna Armstrong-Ivory | F75: 46346 | G75: Not Started | H75: 0 | I75: Final scheduled session is 11/20/26; delivery wraps ahead of Thanksgiving per Renee Raffalli's direction. Calculated date on the Training Capacity Plan tab is 11/22/26. Re-dated 9/15/26 to align with ESC deck v1.24. Final session is 11/20. | J75: n/a - not a comms task
A76: 75 | B76: Copilot Basic | Phase 2 - Monitoring & Continuous Improvement (ongoing) | C76: Task | D76: Staff Office Hours for 4 weeks after each session | E76: AI CoE, Champion Network | G76: Not Started | H76: 0 | I76: Resourced with dedicated time, not a volunteer afterthought | J76: 5 - Sustainment
A77: 76 | B77: Copilot Basic | Phase 2 - Monitoring & Continuous Improvement (ongoing) | C77: Task | D77: Keep Champion Channel open indefinitely | E77: AI CoE, Champion Network | G77: Not Started | H77: 0 | J77: 5 - Sustainment
A78: 77 | B78: Copilot Basic | Phase 2 - Monitoring & Continuous Improvement (ongoing) | C78: Task | D78: Run recurring Prompt-a-thon events | E78: AI CoE, Champion Network | G78: Not Started | H78: 0 | I78: Produces reusable 'book of prompts'; also serves as organic feedback | J78: 5 - Sustainment
A79: 78 | B79: Copilot Basic | Phase 2 - Monitoring & Continuous Improvement (ongoing) | C79: Task | D79: Publish monthly newsletter on citywide progress and usage stories | E79: Tawanna Armstrong-Ivory, Innovations Team (Vikki) | G79: Not Started | H79: 0 | I79: Draws on Copilot Dashboard and survey data | J79: 5 - Sustainment
A80: 79 | B80: Copilot Basic | Phase 2 - Monitoring & Continuous Improvement (ongoing) | C80: Task | D80: Ongoing Copilot Dashboard monitoring against locked success metrics | E80: Tawanna Armstrong-Ivory, Atri Manthani, AI CoE, Business Case Lead, Data & Analytics Team, Data Engineering Team (Pipeline) | G80: Not Started | H80: 0 | I80: Reported to ESC/Cabinet on agreed cadence; data has up to 72-hr latency - plan weekly, not daily, refresh | J80: n/a - not a comms task
A81: 80 | B81: Copilot Basic | Phase 2 - Monitoring & Continuous Improvement (ongoing) | C81: Task | D81: Build consolidated Power BI rollup dashboard (Operational + Strategic + Compliance tiers) | E81: Tawanna Armstrong-Ivory, Atri Manthani, Data & Analytics Team, Data Engineering Team (Pipeline) | G81: Not Started | H81: 0 | I81: Single rollup for ESC/Cabinet rather than five disconnected reports | J81: n/a - not a comms task
A82: 81 | B82: Copilot Basic | Phase 2 - Monitoring & Continuous Improvement (ongoing) | C82: Task | D82: Track thumbs-up/down in-chat feedback and Prompt-a-thon output as organic signal | E82: Atri Manthani, Tawanna Armstrong-Ivory | G82: Not Started | H82: 0 | I82: Confirm which native quality signals surface in the admin reporting tier available to the City | J82: 5 - Sustainment
A83: 82 | B83: Copilot Basic | Phase 2 - Monitoring & Continuous Improvement (ongoing) | C83: Task | D83: Monitor for sensitive data moving to outside AI tools using Microsoft Defender for Cloud Apps | E83: Rajan Sharma (Cybersecurity), AI CoE | G83: Not Started | H83: 0 | I83: Already included with our existing G5 license - no new procurement. Serves as the data-exfiltration safety net for Copilot Basic; Purview is not being used for this rollout, so Defender for Cloud Apps carries this function on its own. | J83: n/a - not a comms task
A84: 83 | B84: Copilot Basic | Phase 2 - Monitoring & Continuous Improvement (ongoing) | C84: Task | D84: Monitoring scope (best practice): usage/adoption trends, data movement to outside AI tools, and AUP/conduct compliance | E84: Atri Manthani, AI CoE | G84: Not Started | H84: 0 | I84: Adoption trends via Copilot Dashboard; data exfiltration via Defender; conduct/AUP issues surfaced through Champion Network reports and periodic governance spot-checks | J84: n/a - not a comms task
A85: 84 | B85: Copilot Basic | Phase 2 - Monitoring & Continuous Improvement (ongoing) | C85: Task | D85: Document monitoring scope and escalation path (no content-level prompt/response monitoring) | E85: Atri Manthani, AI CoE | G85: Not Started | H85: 0 | I85: Copilot Basic is monitored for usage and adoption, not prompt- and response-level content. This is the agreed scope for this rollout, not a pending gap - Purview is not required for Copilot Basic and is not part of this initiative. Serious incidents route through a Champion Network report or a Defender for Cloud Apps flag to open a case. Keep this distinction accurate in ESC materials and in the approved media lines. Revisit if scope expands beyond Copilot Basic Chat or regulated-data use cases are introduced. | J85: n/a - not a comms task
A86: 85 | B86: Copilot Basic | Phase 2 - Monitoring & Continuous Improvement (ongoing) | C86: Task | D86: M365 Admin Center Copilot Usage Report - monthly export (90-day window) | E86: Atri Manthani, AI CoE | G86: Not Started | H86: 0 | I86: Exported monthly as CSV and retained in City-owned storage (SharePoint/Data & Analytics Team) to preserve a historical record beyond the report's rolling 90/180-day window; complements the 30-day Copilot Dashboard view used for weekly monitoring | J86: n/a - not a comms task
A87: 86 | B87: Copilot Basic | Phase 2 - Monitoring & Continuous Improvement (ongoing) | C87: Task | D87: Publish ongoing Tips and Best Practices (quick-hit emails/short videos) | E87: Tawanna Armstrong-Ivory, Innovations Team (Vikki) | G87: Not Started | H87: 0 | I87: Per Comms Roadmap Phase 5 - Sustainment; highlights hidden features, shortcuts, or advanced tips | J87: 5 - Sustainment
A88: 87 | B88: Copilot Basic | Phase 2 - Monitoring & Continuous Improvement (ongoing) | C88: Task | D88: Post Success Stories Showcase on the Hub | E88: Tawanna Armstrong-Ivory, Innovations Team (Vikki) | G88: Not Started | H88: 0 | I88: Per Comms Roadmap Phase 5 - Sustainment; highlights how teams/departments are using Copilot Source stories through the Champion Network or a separate opt-in form on the Hub, not the pulse surveys - the surveys are anonymous, so responses cannot be attributed or permission sought. | J88: 5 - Sustainment
A89: 88 | B89: Copilot Basic | Phase 2 - Monitoring & Continuous Improvement (ongoing) | C89: Task | D89: Route Comms Roadmap Feedback Survey through the pulse survey cycle | E89: Tawanna Armstrong-Ivory, Atri Manthani | G89: Not Started | H89: 0 | I89: Comms Roadmap Phase 5 deliverable. No separate feedback instrument is built - feature requests, improvement areas, and lingering issues are captured through the existing pulse surveys: the post-training blocker and follow-up-topic questions, and the 90-day drop-off, unclear-permission, and biggest-unlock questions. Route anything the pulse surveys do not catch (day-to-day bugs) to the Support Contacts directory and the live FAQ/Known Issues document rather than a new survey. Update the Comms Roadmap so Phase 5 points at the pulse cycle. | J89: 5 - Sustainment
... A91: 90 | B91: Copilot Basic | Phase 2 - Monitoring & Continuous Improvement (ongoing) | C91: Task | D91: Regularly update Hub FAQ page based on real-time employee feedback | E91: Innovations Team (Vikki - Hub) | G91: Not Started | H91: 0 | I91: Per Comms Roadmap Phase 2 - Understanding (Marketing Opportunities), continued as an ongoing practice | J91: 2 - Understanding
A92: 91 | B92: Copilot Basic | Phase 0 - Readiness (through 9/11) | C92: Task | D92: Build pre, post, and 90-day surveys in Microsoft Forms and test end to end | E92: Tawanna Armstrong-Ivory, Innovations Team (Daisha, Vikki) | F92: 46276 | G92: Complete | H92: 1 | I92: All three question sets are drafted (tasks 21-23). Build in Forms/Viva, confirm the repeated items are identical across all three instruments, verify response export into the reporting pipeline, and pilot with the AI CoE before 9/11 ESC. Set all instruments to authenticated (record work email) so responses join to the Teams attendance export. | J92: 3 - Readiness
A93: 92 | B93: Copilot Basic | Phase 0 - Readiness (through 9/11) | C93: Task | D93: Configure pulse surveys as fully anonymous and verify no identity fields are captured | E93: Atri Manthani, Tawanna Armstrong-Ivory | F93: 46276 | G93: In Progress | H93: 0.5 | I93: Approach decided 8/27: surveys are 100% anonymous. No name, work email, or self-generated code is collected - session date only. In Microsoft Forms, turn off 'record name' and set the form to accept responses from anyone with the link; verify on a test submission that no identity column appears in the export before the first live session. Consequence accepted: pre and post results are reported as group averages and distributions by session date, not as matched pairs. Pre-survey respondents and post-survey respondents are not guaranteed to be the same people, so reported lift may be influenced by respondent mix - state this limitation explicitly in ESC reporting rather than implying a matched result. Teams attendance reports remain the attendance record and adoption roster and are kept separate from survey responses. Note: the Forms configuration reminder was removed from the survey documents themselves in v1.4, so the not-record-names setting and the pre-launch test submission are tracked here only - confirm both before the first live session. | J93: 3 - Readiness
A94: 93 | B94: Copilot Basic | Phase 1 - Rolling Training Delivery (9/21/26 onward; see Training Capacity Plan tab) | C94: Task | D94: Issue pre-training pulse survey with each session invite | E94: Tawanna Armstrong-Ivory, Comms, AI CoE, Brian Umerley | F94: 46335 | G94: In Progress | H94: 0.2 | I94: Sent with the session invite ahead of every scheduled session across the 11/9-11/20 window; link lives in the comms email blast template. Brian Umerley confirms the link is present in every invitation before send. | J94: 3 - Readiness
A95: 94 | B95: Copilot Basic | Phase 1 - Rolling Training Delivery (9/21/26 onward; see Training Capacity Plan tab) | C95: Task | D95: Issue post-training pulse survey at the close of each session | E95: AI CoE / Microsoft, Innovations Team (Vikki - Hub), Brian Umerley | F95: 46335 | G95: Not Started | H95: 0 | I95: Delivered in-session at close alongside the Quick Reference slide and Official Training Manual; hold the last three minutes for it. Brian Umerley confirms with Microsoft that the post-session survey is issued in session at close. Survey is anonymous (session date only); the Teams attendance export is captured separately and is never joined to survey responses. | J95: 4 - Action & Go-Live
A96: 95 | B96: Copilot Basic | Phase 1 - Rolling Training Delivery (9/21/26 onward; see Training Capacity Plan tab) | C96: Task | D96: Report running pre/post confidence lift at the rollout midpoint checkpoint | E96: Tawanna Armstrong-Ivory, Atri Manthani | G96: Not Started | H96: 0 | I96: Feeds the midpoint go/no-go on pace; pairs survey confidence lift with Copilot Dashboard adoption data so ESC sees both capability and usage. | J96: 4 - Action & Go-Live
A97: 96 | B97: Copilot Basic | Phase 2 - Monitoring & Continuous Improvement (ongoing) | C97: Task | D97: Field 30-day interim mini-pulse (intent-to-use and blocker questions only) | E97: Tawanna Armstrong-Ivory, Innovations Team (Daisha) | F97: 46377 | G97: Not Started | H97: 0 | I97: Two questions repeated from the post-survey (5-day intent-to-use and remaining blocker) fielded 30 days after the final session on 11/20/26. Confirm the send date against the holiday period - a late-December send may depress response rates. | J97: 5 - Sustainment
A98: 97 | B98: Copilot Basic | Phase 2 - Monitoring & Continuous Improvement (ongoing) | C98: Task | D98: Field 90-day follow-up survey | E98: Tawanna Armstrong-Ivory, Innovations Team (Daisha, Vikki) | F98: 46436 | G98: Not Started | H98: 0 | I98: Fielded 90 days after the final session (11/20/26). Measures realized usage against the pre-survey baseline and post-survey intent; drop-off question distinguishes a training gap from a licensing or policy gap. | J98: 5 - Sustainment
A99: 98 | B99: Copilot Basic | Phase 2 - Monitoring & Continuous Improvement (ongoing) | C99: Task | D99: Announce 30-day and 90-day surveys across all internal comms channels | E99: Tawanna Armstrong-Ivory, Innovations Team (Vikki), Comms | F99: 46433 | G99: Not Started | H99: 0 | I99: Per Comms Roadmap Phase 5 - Sustainment. Push through newsletter, Hub, AppSpace, and Teams channel (any internal comms channel) in the same week the survey is fielded. Response rates on post-training follow-ups fall sharply without a comms push; pair each survey with a Success Stories or Tips post in the same week. | J99: 5 - Sustainment
A100: 99 | B100: Copilot Basic | Phase 2 - Monitoring & Continuous Improvement (ongoing) | C100: Milestone | D100: Publish consolidated survey findings (pre / post / 30-day / 90-day) to ESC and Cabinet | E100: Tawanna Armstrong-Ivory, Atri Manthani, Renee Raffalli | F100: 46447 | G100: Not Started | H100: 0 | I100: Headline reporting: confidence lift (pre vs. post vs. 90-day), realized usage vs. intent, time saved, and the ranked blocker list that scopes the intermediate-session decision. | J100: 5 - Sustainment
A101: 100 | B101: Copilot Basic | Phase 0 - Readiness (through 9/11) | C101: Task | D101: Review and approve pre, post, and 90-day survey instruments (v1.4) | E101: Renee Raffalli, Atri Manthani, Innovations Team (Daisha) | F101: 46269 | G101: Not Started | H101: 0 | I101: Drafts created 8/27, revised through v1.4. Approval needed before the Forms build (task 80) so the repeated items are locked - any rewording after build breaks comparability across the three instruments. Confirm the anonymity decision at the same time, since it is what allows candid answers on the blocker and acceptable-use questions. | J101: 3 - Readiness
A102: 101 | B102: Copilot Basic | Phase 0 - Readiness (through 9/11) | C102: Task | D102: Hold Manager awareness and alignment meeting (leadership alignment meeting / memo) | E102: Tawanna Armstrong-Ivory, Atri Manthani, Renee Raffalli | F102: 46276 | G102: Not Started | H102: 0 | I102: Comms Roadmap Phase 1 - Awareness, Managers audience. Distinct from the Chiefs & Directors email (task 10): managers need a live alignment touchpoint plus a memo, since they field the first questions from their teams. | J102: 1 - Awareness
A103: 102 | B103: Copilot Basic | Phase 0 - Readiness (through 9/11) | C103: Task | D103: Hold Department Representatives project overview and expectations session | E103: Tawanna Armstrong-Ivory, Atri Manthani | F103: 46276 | G103: Not Started | H103: 0 | I103: Comms Roadmap Phase 1 - Awareness, Department Representatives audience. Teams or in-person overview covering rollout scope and what departments are expected to do. | J103: 1 - Awareness
A104: 103 | B104: Copilot Basic | Phase 0 - Readiness (through 9/11) | C104: Task | D104: Produce Manager Guide (physical/digital) and run manager workshop | E104: Tawanna Armstrong-Ivory, Innovations Team (Vikki - design) | F104: 46276 | G104: Not Started | H104: 0 | I104: Comms Roadmap Phase 2 - Understanding, Managers/Team Leads audience. Equips managers to support their teams during rollout; no manager-specific asset currently exists in the plan. | J104: 2 - Understanding
A105: 104 | B105: Copilot Basic | Phase 0 - Readiness (through 9/11) | C105: Task | D105: Schedule department-level meetings and Q&A sessions | E105: Tawanna Armstrong-Ivory, Department Representatives | G105: Not Started | H105: 0 | I105: Comms Roadmap Phase 2 - Understanding, Department Representatives audience. Department-level support and information sharing ahead of the training window. | J105: 2 - Understanding
A106: 105 | B106: Copilot Basic | Phase 0 - Readiness (through 9/11) | C106: Decision | D106: Select the 2-3 key benefits used across all launch messaging | E106: Tawanna Armstrong-Ivory, Atri Manthani, Renee Raffalli | F106: 46269 | G106: Complete | H106: 1 | I106: Comms Roadmap lists candidate benefits (shadow AI risk reduction, time back on routine writing, no additional licensing cost, foundation for later AI tiers). Pick 2-3 and use them verbatim across the Leadership Announcement, Overview Document, signage, and session openers - inconsistent benefit messaging is the most common reason a launch narrative does not land. The same benefits carry into the press release, so select them with an external audience in mind. | J106: 1 - Awareness
A107: 106 | B107: Copilot Basic | Phase 0 - Readiness (through 9/11) | C107: Task | D107: Produce launch announcement video message | E107: Innovations Team (Vikki - design), Tawanna Armstrong-Ivory | G107: Not Started | H107: 0 | I107: Comms Roadmap Phase 1 lists video as an employee channel alongside email and intranet; currently only written messages are in the plan. | J107: 1 - Awareness
A108: 107 | B108: Copilot Basic | Phase 1 - Rolling Training Delivery (9/21/26 onward; see Training Capacity Plan tab) | C108: Task | D108: Publish Office Hours schedule (virtual/in-person support rooms) at go-live | E108: Tawanna Armstrong-Ivory, AI CoE, Innovations Team (Vikki - Hub) | G108: Not Started | H108: 0 | I108: Comms Roadmap Phase 4 deliverable. Task 63 staffs office hours after each session; this is the published calendar and drop-in support rooms for the launch window itself. | J108: 4 - Action & Go-Live
A109: 108 | B109: Copilot Basic | Phase 2 - Monitoring & Continuous Improvement (ongoing) | C109: Task | D109: Update Comms Roadmap to include the pulse survey cycle | E109: Tawanna Armstrong-Ivory | G109: Not Started | H109: 0 | I109: Add the pre, post, 30-day and 90-day pulse instruments to Comms Roadmap Phase 5 and point the Phase 5 'Feedback Survey' deliverable at them rather than describing a separate pipeline. Ensures the follow-up survey pushes are planned as comms events and that there is one feedback channel, not two competing ones. | J109: 5 - Sustainment
A110: 109 | B110: Copilot Basic | Phase 0 - Readiness (through 9/11) | C110: Task | D110: Establish comms distribution and approval workflow (all launch messaging approved by Renee/Liz before send) | E110: Tawanna Armstrong-Ivory, Renee Raffalli, Liz, Comms | F110: 46269 | G110: Not Started | H110: 0 | I110: All citywide Copilot Basic messaging - Leadership Announcement, Chiefs & Directors email, session invites, Go-Live Announcement, newsletters, AppSpace signage, and survey pushes - requires Renee/Liz approval before distribution. Roles per Comms Roadmap: design Vikki Pickett; message development Tawanna and Atri; distribution Comms with Renee/Liz approving. Agree the turnaround time for approvals at the same time, since every dated comms task depends on it. External media communications run through Marie Zickefoose and follow the same Renee/Liz approval path before release. | J110: 1 - Awareness
A111: 110 | B111: Copilot Basic | Phase 0 - Readiness (through 9/11) | C111: Task | D111: Confirm session recording approach and consent language for Hub publication | E111: Tawanna Armstrong-Ivory, Atri Manthani, ITS | F111: 46276 | G111: Not Started | H111: 0 | I111: Sessions must be recorded to feed the BizLibrary onboarding module. Confirm Teams cloud recording is enabled for every scheduled session, agree who starts and stores the recording, and add a recording notice to the session invite and the session opener. Decide up front whether attendee video and chat are captured or suppressed - recordings reused for onboarding are viewed by people who were not in the room. BizLibrary is being retired as the document source (noted 9/15/26); the hosting destination for recordings and the onboarding module must be re-decided. See D17. Destination resolved 9/15/26: the Resource Hub, not BizLibrary. See D17. | J111: 3 - Readiness
A112: 111 | B112: Copilot Basic | Phase 1 - Rolling Training Delivery (9/21/26 onward; see Training Capacity Plan tab) | C112: Task | D112: Record each training session for Hub reuse | E112: AI CoE / Microsoft, Innovations Team (Vikki - Hub) | F112: 46335 | G112: Not Started | H112: 0 | I112: Record every session; capture the clean master of the unified curriculum for the onboarding module. Store recordings centrally as they are produced rather than retrieving them later - Teams/Stream retention policies are finite and the December recording must survive until the module is built in January. BizLibrary is being retired as the document source (noted 9/15/26); the hosting destination for recordings and the onboarding module must be re-decided. See D17. Destination resolved 9/15/26: the Resource Hub, not BizLibrary. See D17. | J112: 4 - Action & Go-Live
A113: 112 | B113: Copilot Basic | Phase 2 - Monitoring & Continuous Improvement (ongoing) | C113: Task | D113: Produce and publish the Copilot Basic new-hire recording on the Resource Hub | E113: Tawanna Armstrong-Ivory, Innovations Team (Vikki - design), HR | F113: 46402 | G113: Not Started | H113: 0 | I113: Edited session recording plus the Quick Reference slide, Official Training Manual, and Do's and Don'ts list, published as a BizLibrary module. Purpose: every new employee completes it as part of onboarding, since Copilot Basic access is granted automatically via Entra ID on day one. Trim to the evergreen curriculum - cut rollout-specific timing, dates, and session logistics that will not make sense to someone starting in 2028. 9/14 - may need to find something else as BizLibrary is going away. BizLibrary is being retired as the document source (noted 9/15/26); the hosting destination for recordings and the onboarding module must be re-decided. See D17. Destination resolved 9/15/26: the Resource Hub, not BizLibrary. See D17. | J113: 5 - Sustainment
A114: 113 | B114: Copilot Basic | Phase 2 - Monitoring & Continuous Improvement (ongoing) | C114: Task | D114: Add Copilot Basic to the standard new-hire onboarding path (Hub recording, software install, Do’s and Don’ts) | E114: Tawanna Armstrong-Ivory, HR, Renee Raffalli | F114: 46402 | G114: Not Started | H114: 0 | I114: Assign the BizLibrary module in the new-hire onboarding sequence and agree the completion expectation and how it is tracked. Without this step the module exists but is never assigned, which is the usual failure mode for onboarding content. ESC direction 9/11/26: handle new hires through an on-demand approach, likely a recording, rather than a separate live path (D5). BizLibrary is being retired as the document source (noted 9/15/26); the hosting destination for recordings and the onboarding module must be re-decided. See D17. Destination resolved 9/15/26: the Resource Hub, not BizLibrary. See D17 New-hire onboarding has three components: a recording on the Resource Hub for new hires to listen to, Copilot Basic installed on new-hire computers, and the Do’s and Don’ts displayed on the Hub. | J114: 5 - Sustainment
A115: 114 | B115: Copilot Basic | Phase 2 - Monitoring & Continuous Improvement (ongoing) | C115: Task | D115: Add Copilot Basic to the new-hire computer build so it is installed at issue | E115: Mike Ruscin, DC Faranak | F115: 46402 | G115: Not Started | H115: 0 | I115: Component two of the new-hire onboarding approach. Builds on the Intune deployment line in Phase 0 so new-hire machines receive Copilot Basic at issue rather than by request. | J115: n/a - not a comms task
A116: 115 | B116: Copilot Basic | Phase 2 - Monitoring & Continuous Improvement (ongoing) | C116: Task | D116: Publish the Do’s and Don’ts on the Resource Hub | E116: Tawanna Armstrong-Ivory, Innovations Team (Vikki) | F116: 46307 | G116: Not Started | H116: 0 | I116: Component three of the new-hire onboarding approach and a citywide reference. The list itself is complete; this line covers display on the Hub when the page goes live 10/12. Keep consistent with the overarching CyberSecurity policy once issued. | J116: C - Citywide
A117: 116 | B117: Copilot Basic | Phase 2 - Monitoring & Continuous Improvement (ongoing) | C117: Task | D117: Review and refresh the Hub new-hire recording and Do’s and Don’ts annually | E117: Tawanna Armstrong-Ivory, AI CoE | G117: Not Started | H117: 0 | I117: Copilot features and City guidance change; an onboarding module recorded in late 2026 will drift. Re-review at least annually, and immediately if Copilot scope expands beyond Chat, Word, Excel, and PowerPoint or the acceptable-use guidance changes. BizLibrary is being retired as the document source (noted 9/15/26); the hosting destination for recordings and the onboarding module must be re-decided. See D17. Destination resolved 9/15/26: the Resource Hub, not BizLibrary. See D17. | J117: 5 - Sustainment
A118: 117 | B118: Copilot Basic | Phase 0 - Readiness (through 9/11) | C118: Task | D118: Draft proactive press release announcing Copilot Basic launch | E118: Marie Zickefoose (Media Relations), Tawanna Armstrong-Ivory, Atri Manthani | F118: 46304 | G118: Not Started | H118: 0 | I118: Proactive external announcement of the citywide Copilot Basic rollout. Message development with Tawanna and Atri; Marie owns the release and media relations. Use the same 2-3 key benefits selected for internal messaging so the external and internal narratives match. Careful wording needed on the shadow AI point - reducing unapproved public AI tool use is a strength internally but reads as an admission of prior exposure in a press release; frame around governed, trained, no-additional-cost access instead. | J118: 1 - Awareness
A119: 118 | B119: Copilot Basic | Phase 0 - Readiness (through 9/11) | C119: Task | D119: Prepare approved media lines on privacy, monitoring, and data handling | E119: Marie Zickefoose (Media Relations), Tawanna Armstrong-Ivory, Atri Manthani, Legal | F119: 46304 | G119: Not Started | H119: 0 | I119: Reporters will ask what the City monitors, whether resident data touches Copilot, and how HIPAA/CJIS-adjacent data is handled. Prepare approved lines covering what is measured (usage and adoption via the Copilot Dashboard and M365 Admin Center), what is not (prompt and response content), and the Defender for Cloud Apps safety net - so answers are consistent and pre-cleared rather than improvised. | J119: 1 - Awareness
A120: 119 | B120: Copilot Basic | Phase 1 - Rolling Training Delivery (9/21/26 onward; see Training Capacity Plan tab) | C120: Milestone | D120: Issue press release (after internal soft launch, on or after Launch Date) | E120: Marie Zickefoose (Media Relations), Renee Raffalli | F120: 46323 | G120: Not Started | H120: 0 | I120: Sequencing is the point: the internal soft launch to Cabinet, Directors, Chiefs, PIOs and Data Leads lands 10/15 and the Launch Date is 10/28. The press release must not precede the soft launch. Coordinate with the Go-Live Announcement so internal and external land together or internal lands first. | J120: 4 - Action & Go-Live
A121: 120 | B121: Copilot Basic | Phase 0 - Readiness (through 9/11) | C121: Decision | D121: Decide Copilot Basic reporting access route: Microsoft O365 reporting connection vs. licensing 50 users | E121: Tawanna Armstrong-Ivory, Atri Manthani, DC Faranak, Renee Raffalli | F121: 46269 | G121: Not Started | H121: 0 | I121: Blocks the Copilot Dashboard configuration task and, through it, every adoption metric. Preferred route: connect to O365 for reporting through Microsoft, avoiding both the 50-license purchase and its associated Microsoft training requirement. Fallback: license 50 users to activate Admin Center reporting. Confirm the O365 connection route with Microsoft and DC Faranak before the 9/11 ESC so metric thresholds are locked against what can actually be measured. | J121: n/a - not a comms task
A122: 121 | B122: HR Chatbot | Readiness & Provisioning (through 10/2) | C122: Task | D122: Complete end-to-end audit workflow testing (Forms, SharePoint List, Power Automate) | E122: Atri Manthani, Tawanna Armstrong-Ivory | F122: 46269 | G122: Complete | H122: 1 | I122: Validates the full testing and audit mechanism before Microsoft training. Confirms evaluation fields captured, Form responses written to the SharePoint List, Power Automate routing and status changes correct, and the audit trail traceable from submission through remediation and retest. | J122: C1 - Project team
A123: 122 | B123: HR Chatbot | Readiness & Provisioning (through 10/2) | C123: Task | D123: Continue preview audit testing through Labor Day week | E123: Atri Manthani | F123: 46276 | G123: In Progress | H123: 0.5 | I123: Controlled preview test cases run through the chatbot and Form to keep the workflow under active validation. Sample remediation and retest scenarios confirm issues can be logged, corrected, retested and traced to closure. | J123: n/a - not a comms task
A124: 123 | B124: HR Chatbot | Readiness & Provisioning (through 10/2) | C124: Task | D124: Hold Microsoft review meeting: chatbot, audit strategy, security group, licensing, training model | E124: Tawanna Armstrong-Ivory, Atri Manthani, Microsoft | F124: 46290 | G124: In Progress | H124: 0.25 | I124: Agenda covers the chatbot walkthrough, testing and validation audit strategy, security-group strategy, licensing strategy and confirmation of the three-session Microsoft training model. Gating call for D14 and D15. Email to Eli 9/14/26 to schedule; agenda includes security group setup, reporting, and license type and capacity. D14 (security group naming and governance) and D15 (license type and capacity) were closed as separate decisions 9/15/26 and are now tracked here. Both must be settled at this meeting. | J124: C2 - Microsoft, project team
A125: 124 | B125: HR Chatbot | Readiness & Provisioning (through 10/2) | C125: Task | D125: Create Entra ID security group for HR Policy Chatbot testing access | E125: Atri Manthani, DC Faranak Arab | F125: 46290 | G125: In Progress | H125: 0.25 | I125: Working name "HR Policy Chatbot - Testing Access", subject to City naming standards. Membership managed in phase-based waves. Training status does not determine group membership or license assignment. Held pending the Microsoft walkthrough (D14); naming subject to City standards. | J125: n/a - not a comms task
A126: 125 | B126: HR Chatbot | Readiness & Provisioning (through 10/2) | C126: Task | D126: Confirm phase-based licensing and membership strategy with the Global Administrator | E126: Tawanna Armstrong-Ivory, Atri Manthani, DC Faranak Arab | F126: 46290 | G126: In Progress | H126: 0.25 | I126: Licenses are assigned by authorized testing phase, not by training completion. Confirm license type, assignment process, available capacity and validation steps. Held pending the Microsoft walkthrough (D15) on license type and capacity. | J126: n/a - not a comms task
A127: 126 | B127: HR Chatbot | Readiness & Provisioning (through 10/2) | C127: Milestone | D127: ESC approval of HR Chatbot communication and testing plans | E127: Tawanna Armstrong-Ivory, AI CoE | F127: 46276 | G127: Complete | H127: 1 | I127: Hard gate. No tester communication is issued before this approval. Agenda item 3 at the 9/11 ESC: scope and status, three-phase test strategy, Microsoft training window, phased licensing, testing timeline. ESC approval received 9/11/26: approval to proceed with HR Policy Chatbot training and testing plans. | J127: C2a - ESC
A128: 127 | B128: HR Chatbot | Readiness & Provisioning (through 10/2) | C128: Task | D128: Create Teams channel for HR Policy Chatbot testing communications | E128: Tawanna Armstrong-Ivory | F128: 46279 | G128: Complete | H128: 1 | I128: Standing channel for communicating with testers across all three phases: announcements, question intake, issue reporting, and reminders. Confirm whether tester communications currently planned as email (supervisor notification, onboarding email, session reminders, follow-ups) should move to or be mirrored in this channel, and update the HR Chatbot Comms Calendar channel column accordingly. | J128: C - Testers, all phases
A129: 128 | B129: HR Chatbot | Readiness & Provisioning (through 10/2) | C129: Task | D129: Send supervisor notification: who is testing, which phase, expected time commitment | E129: Tawanna Armstrong-Ivory | F129: 46276 | G129: Complete | H129: 1 | I129: Held until after ESC approval on 9/11. | J129: C3 - Supervisors
... A140: 139 | B140: HR Chatbot | Readiness & Provisioning (through 10/2) | C140: Task | D140: Confirm HIPAA BAA and CJIS coverage for the HR Policy Chatbot stack (Copilot Studio and Dataverse) | E140: Tawanna Armstrong-Ivory, IT Security (Rajan Sharma, Peter Rodenberg) | F140: 46304 | G140: Complete | H140: 1 | I140: Separate from the Copilot Basic BAA/CJIS confirmation - a different service, storage location and data flow. Confirm coverage for Copilot Studio and for Dataverse, where conversation transcripts are retained and from which transcripts are pulled during an incident review. Triggered by the content inventory; if regulated data is in the grounded sources, treat this as a hard gate before pilot deployment rather than a production-gate item. Target completion before the Phase 1 gate so it does not surface at the 11/30 ESC. | J140: n/a - not a comms task
A141: 140 | B141: HR Chatbot | Readiness & Provisioning (through 10/2) | C141: Task | D141: Maintain the access and training tracker (name, phase, group date, license status, access validation, training completion) | E141: Tawanna Armstrong-Ivory, Brian Umerley (backup) | G141: Not Started | H141: 0 | I141: Training completion is tracked as a separate readiness item and is never the trigger for access or licensing. Reviewed weekly with DC Faranak Arab during training and testing. Brian Umerley serves as backup for tracker maintenance; availability not confirmed, so primary ownership stays with Tawanna. | J141: n/a - not a comms task
A142: 141 | B142: HR Chatbot | Readiness & Provisioning (through 10/2) | C142: Task | D142: Reconcile missing testers against the tracker and supply participation figures for leadership updates | E142: Tawanna Armstrong-Ivory, Brian Umerley (backup) | G142: Not Started | H142: 0 | I142: Brian Umerley reconciles non-attendees and missing testers against the training and access tracker and flags gaps. Figures feed the leadership and launch updates: Copilot Basic adoption and HR Chatbot training progress. Brian Umerley serves as backup for tracker reconciliation; availability not confirmed, so primary ownership stays with Tawanna. | J142: n/a - not a comms task
A143: 142 | B143: HR Chatbot | Three-Phase Testing (10/5-11/20) | C143: Milestone | D143: Phase 1 testing opens - 15 named testers | E143: Tawanna Armstrong-Ivory | F143: 46300 | G143: Not Started | H143: 0 | I143: Two weeks, 9/28-10/9. Testers execute assigned questions, evaluate correctness, completeness, relevance and policy alignment, verify source grounding and citations, and log results in the Microsoft Form. Re-dated 9/15/26 to align with ESC deck v1.24. Phase 1 testing runs 10/5 to 10/16. Previously 09/28/26. | J143: C14 - Email plus Teams post
A144: 143 | B144: HR Chatbot | Three-Phase Testing (10/5-11/20) | C144: Task | D144: Phase 1 week 1 pulse and deadline reminder | E144: Tawanna Armstrong-Ivory | F144: 46304 | G144: Not Started | H144: 0 | I144: Pulse 10/2 covering submissions to date, themes and coverage gaps; deadline reminder 10/7 for results due 10/9. Re-dated 9/15/26 to align with ESC deck v1.24. Previously 10/07/26. | J144: C15, C16 - Phase 1
A145: 144 | B145: HR Chatbot | Three-Phase Testing (10/5-11/20) | C145: Milestone | D145: Phase 1 testing closes | E145: Tawanna Armstrong-Ivory | F145: 46311 | G145: Not Started | H145: 0 | I145: Close notice explains what the gate week involves. Re-dated 9/15/26 to align with ESC deck v1.24. Previously 10/09/26. | J145: C17 - Phase 1
A146: 145 | B146: HR Chatbot | Three-Phase Testing (10/5-11/20) | C146: Milestone | D146: Phase 1 evaluation and remediation gate | E146: Tawanna Armstrong-Ivory, Atri Manthani | F146: 46318 | G146: Not Started | H146: 0 | I146: Week of 10/12-10/16. Consolidate results and metrics, identify recurring issues and grounding gaps, remediate, retest without regression, confirm critical issues closed or dispositioned. Leadership approval required before Phase 2 begins. Retest confirmations requested 10/13; results and approval request 10/15; decision communicated 10/16. Re-dated 9/15/26 to align with ESC deck v1.24. Gate runs 10/19 to 10/23. Previously 10/16/26. | J146: C18, C19, C20 - Phase 1, Phase 2, Leadership
A147: 146 | B147: HR Chatbot | Three-Phase Testing (10/5-11/20) | C147: Task | D147: Provision Phase 2 after Phase 1 approval | E147: Atri Manthani, DC Faranak Arab, Rajan Sharma, Peter Rodenberg | F147: 46318 | G147: Not Started | H147: 0 | I147: Dustin Hargis, Patrick Lang and Matt Hetrick added to the security group and licensed only on Phase 2 authorization; access confirmed before testing begins. Re-dated 9/15/26 to align with ESC deck v1.24. Previously 10/16/26. | J147: C21 - 3 Phase 2 testers
A148: 147 | B148: HR Chatbot | Three-Phase Testing (10/5-11/20) | C148: Milestone | D148: Phase 2 HR business testing opens - 3 testers | E148: Tawanna Armstrong-Ivory | F148: 46314 | G148: Not Started | H148: 0 | I148: Two weeks, 10/19-10/30. Focus on policy accuracy in realistic HR business scenarios, source grounding and traceability, and missing policy coverage. Week 1 check-in 10/23; deadline reminder 10/28. | J148: C22, C23, C24 - Phase 2
...

Sheet Key Dates & Milestones
A1: Date | B1: Milestone | C1: Deliverables Due
A2: 46258 | B2: Analytics & dashboard readiness | C2: Analytics Monitoring Plan draft; Communications Plan draft; adoption success metrics and thresholds locked; Copilot Dashboard (Viva Insights) access configured
A3: 46262 | B3: Training plan & sign-up process finalized | C3: Roll Out Plan draft sized to ~5,606 E5 employees across a rolling multi-session schedule; training sign-up/attendance method finalized. F3 (field, ~1,801) out of scope for this phase
A4: 46269 | B4: Reinforcement infrastructure in place | C4: Pre, post, and 90-day survey question sets designed (complete 8/27); reinforcement activities scheduled (Prompt-a-thon, Great Copilot Journey). Surveys built and tested in Microsoft Forms by 9/11.
A5: 46276 | B5: ESC approval | C5: Plans presented to ESC for final approval (first ESC meeting), including the revised multi-session, multi-month training schedule
A6: 46276 | B6: HR Chatbot: ESC approval of communication and testing plans | C6: Hard gate. No tester communication is issued before this approval.
A7: 46297 | B7: HR Chatbot: Microsoft training window complete | C7: Three standardized sessions delivered. Session 1 (Phase 1 and Phase 2) 9/28; Phase 3 Cohort A 10/27 and Cohort B 10/29 per ESC deck v1.24. Follow-ups and make-up options issued by 10/2.
A8: 46301 | B8: Soft launch: Cabinet presentation with Council | C8: Rationale for the rollout, logistics, the training plan and the Resource Hub. Follow-up email includes a Copilot link for preview. Data Leads meeting 10/8; Resource Hub page live and AppSpace posting begins 10/12.
A9: 46311 | B9: HR Chatbot: Phase 1 testing complete (15 named testers) | C9: Testing runs 10/5 to 10/16. Gate week 10/19-10/23: evaluate, remediate, retest, Leadership approval to provision Phase 2.
A10: 46323 | B10: Launch Date | C10: Citywide launch - Copilot Basic link and getting-started basics provided; launch communication sent Friday 10/30 ahead of the 11/2-11/6 self-guided familiarization week. Date moved from 10/31 to 10/28 per Rollout Plan v1.9.
A11: 46323 | B11: Press release issued (external launch announcement) | C11: Proactive announcement of the citywide Copilot Basic rollout, owned by Marie Zickefoose. Must follow the 10/15 internal soft launch; coordinate with the Go-Live Announcement so internal lands first or together
A12: 46325 | B12: HR Chatbot: Phase 2 HR business testing complete (3 testers) | C12: Testing runs 10/19 to 10/30. Gate week 11/2-11/6: evaluate, remediate, retest, Leadership approval to provision Phase 3.
A13: 46335 | B13: Live training sessions begin | C13: Session 1 of six (11/9, 11/11, 11/13, 11/16, 11/18, 11/20), 1.5 hours each, three per week, delivered by Microsoft over Teams. Same curriculum repeated at every session. Champion Network recruitment begins.
... A20: 46447 | B20: Consolidated survey findings to ESC/Cabinet | C20: Confidence lift across all four instruments, realized vs. intended usage, time saved, and ranked blockers scoping the intermediate-session decision
A22: Column key
A23: Comms Phase: maps each Project Plan line to the corresponding touchpoint in the Copilot Systems Launch Comms Roadmap and the HR Policy Chatbot Communication Plan v4.0. Values reference the touchpoint ID and audience (for example, C33 - Phase 3). Lines with no associated communication are marked 'n/a - not a comms task'.

Sheet Risks & Open Decisions
A1: Key Risks & Mitigations
A2: ID | B2: Risk | C2: Mitigation | D2: Likelihood | E2: Impact
A3: R1 | B3: Compressed two-week delivery window (11/9-11/20) leaves no recovery room if sessions slip or attendance lags | C3: Six sessions repeat the same curriculum, so a missed session is recoverable within the window. Track attendance against the 5,606 target after each session and escalate at the 11/13 midpoint if pace is short; sessions are recorded, and the BizLibrary module plus Copilot Academy carry anyone who cannot attend live. | D3: Medium | E3: High
A4: R2 | B4: First-comms clarity on how to actually use the tool | C4: Copilot Basic Chat is a simple rollout and many employees are already familiar with chat AI personally, so a logistics dry-run is not required. The real exposure is the first communication: if it does not clearly show employees how to reach the tool and what to try first, early momentum is lost before training begins. Make the launch comms tight and concrete - the Copilot Basic link, first-use steps, and a handful of try-this-today prompts - paired with the Quick Reference and Hub content. | D4: Medium | E4: Medium
A5: R3 | B5: Reinforcement under-investment | C5: Employees revert to public AI tools once training ends if reinforcement is not sustained. Resource Office Hours, the Champion Network, Prompt-a-thon and the Great Copilot Journey as ongoing commitments, not one-off events. Gemini is not in scope for the crawl phase - no one will have access. Placeholder to watch: there have been discussions about disabling Copilot Chat; not confirmed. If that advances it materially changes both the reinforcement plan and the rollout itself, so track it and confirm status before 9/11. | D5: Medium | E5: High
A6: R4 | B6: Regulated-data exposure | C6: PHI or CJIS-regulated data could reach Copilot before a BAA/CJIS Addendum is signed. Treat BAA/CJIS confirmation as a hard blocking gate - no session content or access assumes regulated-data readiness until written confirmation is issued. Closed for Copilot Basic on 9/10/26 per D8: data remains in tenant, no BAA or CJIS addendum required. Residual exposure is limited to the HR Chatbot grounded content, tracked at R14 and D16. | D6: Low | E6: High
A7: R5 | B7: Metric drift | C7: Redefining metrics mid-rollout makes progress unprovable to the ESC. Lock metric definitions in writing before the 9/11 ESC presentation; any change to definitions requires ESC notification, not silent revision. | D7: Medium | E7: Medium
A8: R6 | B8: Undecided open items | C8: Public-LLM policy and new-hire orientation approach remain open decisions. Resolve both before 9/11, or explicitly present them to ESC as named open risks with a target resolution date. | D8: High | E8: Medium
A9: R7 | B9: Monitoring and audit expectations for Copilot Basic | C9: Confirmed 8/28 and re-confirmed with Rajan Sharma (CyberSecurity) that Purview is not required for the Copilot Basic rollout; all Purview, DSPM and Communication Compliance tasks were removed from the plan on that basis. Monitoring runs through the Copilot Dashboard (Viva Insights) and M365 Admin Center reporting, with Microsoft Defender for Cloud Apps covering data movement to outside AI tools. Rajan also requested a CyberSecurity test run of Copilot Basic before the 10/15 soft launch, tracked as a Phase 1 task. Keep the expectation accurate in ESC materials and media lines: usage and adoption are measured, prompt- and response-level content is not. Revisit if scope expands beyond Copilot Basic Chat or regulated-data use cases are introduced. Purview remains a conditional production-readiness requirement for the HR Policy Chatbot if its production scope includes sensitive or regulated data. | D9: Low | E9: Low
A10: R8 | B10: No usage/adoption reporting mechanism in place | C10: Copilot Basic reporting is not yet activated. Without it there is no usage or adoption data and the metrics committed to ESC cannot be produced. Preferred route is a Microsoft O365 reporting connection, which avoids the 50-license purchase and its training dependency; licensing 50 users remains the fallback. Confirm the route with Microsoft and DC Faranak before 9/11 so thresholds are locked against what can be measured. | D10: Medium | E10: High
A11: R9 | B11: HR Chatbot: testers assume training completion grants chatbot access | C11: State the separation in the onboarding email, in every training follow-up and in each provisioning notice. Security-group membership and licensing are activated only when the phase is formally authorized. | D11: Medium | E11: Medium
A12: R10 | B12: HR Chatbot: the 9/11 ESC approval slips, compressing onboarding against a 9/14 training start | C12: C3, C4 and C5 are held until after ESC approval. Escalate the same day if approval moves; if it slips past 9/11, training invitations and the Microsoft window move with it rather than sending tester communication ahead of approval. | D12: Medium | E12: High
A13: R11 | B13: HR Chatbot: approximately 80 Generalists provisioned at once creates an access support spike | C13: Provisioning and the service desk brief both land 11/6 for a 11/9 start, with a triage script and FAQ in hand and a weekly service desk sync through Phase 3. | D13: Medium | E13: Medium
... A17: R15 | B17: Sustainment path breaks: BizLibrary retiring leaves recordings and the onboarding module without a home | C17: Closed 9/15/26: the Resource Hub replaces BizLibrary for the new-hire recording and the Do’s and Don’ts (D17, D5). Remaining action is to confirm Hub retention and access settings before recording begins 11/9. | D17: Low | E17: Low
A19: Open Decisions
A20: ID | B20: Decision | C20: Status | D20: Target Resolution | E20: Notes
A21: D1 | B21: Confirmed session capacity and cadence for ~7,407 employees | C21: Resolved 9/4 | D21: 46262 | E21: Resolved: six Microsoft-delivered sessions of 1.5 hours each, three per week across 11/9-11/20, open enrollment with no attendance cap. Same curriculum at every session.
A22: D2 | B22: Registration model for virtual E5 sessions | C22: Resolved 8/27 | D22: 46262 | E22: Resolved: no registration required of employees. Sessions are delivered as Webinar in Teams rather than a standard Teams meeting, chosen for capacity at the 5,606-employee scale. The Copilot Basic link and session links go out through the comms plan. Attendance is captured from the Teams report and serves as the adoption-tracking roster. Open mechanic to confirm with Brad Beran: which report the webinar format produces and that it carries name and work email, since that export feeds the cumulative attendance count and the adoption metrics.
A23: D3 | B23: Training strategy - department-based vs. open enrollment | C23: Resolved 9/4 | D23: 46262 | E23: Resolved: open enrollment. Employees self-select into any of the six sessions rather than being scheduled by department; attendance is tracked from the Teams attendance report against the 5,606 target.
A24: D4 | B24: Plan to address public LLM use | C24: In Progress | D24: 46295 | E24: We will offer a recommendation to ESC on 9/11 meeting. Presented to ESC 9/11/26. Doug Meil is taking the lead on the recommendation. Tawanna developed a draft that transfers to Doug as the starting point. Confirm the target date for his recommendation back to the ESC. Update 9/15/26: Doug Meil is leading the policy recommendations. A draft has been placed in the folder, using Boston as the example. A target schedule was provided on the ESC call, ahead of the 10/6 rollout to Cabinet.
A25: D5 | B25: New-hire orientation approach for Copilot | C25: Resolved 9/15 | D25: 46280 | E25: With training now spanning 3-4+ months on a rolling basis, new hires may be able to join the next scheduled session rather than needing a fully separate path - confirm approach. Discussed at ESC 9/11/26. Direction is to handle new hires through an on-demand approach, likely a recording, rather than a separate live session path. Confirm the format, where it is hosted, and who owns production. Resolved 9/15/26. Three components: a recording on the Resource Hub for new hires, Copilot Basic installed on new-hire computers, and the Do’s and Don’ts displayed on the Hub. No separate live session path for new hires.
A26: D6 | B26: Adoption success metrics and thresholds | C26: Resolved 9/4 | D26: 46258 | E26: Resolved and locked for ESC: Training Reach 5,606; Retention 50% of new users returning within 30 days; Habitual Use 30% of users active at least three distinct days per week; Sustained Use 50% of trained employees using Copilot weekly at 90 days; Capability measured as confidence lift pre, post and at 90 days.
A27: D7 | B27: Week-over-week retention threshold | C27: Resolved 9/4 | D27: 46276 | E27: Resolved: retention threshold set at 50% of new Copilot users returning and using it again within 30 days, per the Measures of Success slide presented to ESC.
A28: D8 | B28: HIPAA BAA / CJIS Security Addendum status | C28: Resolved 9/10 | D28: 46275 | E28: Required before any regulated-data content is included; tracked until written confirmation is issued. Resolved 9/10/26 with Rajan Sharma: no HIPAA BAA or CJIS Security Addendum is required for Copilot Basic. Data stays within the tenant and is not made public. This resolution covers Copilot Basic only. D16, whether a separate HIPAA determination is required for the HR Policy Chatbot grounded content, remains open pending the content inventory.
A29: D9 | B29: Survey anonymity vs. matched pre/post analysis | C29: Resolved 8/27 | D29: 46276 | E29: Resolved: surveys are fully anonymous - session date only, no name, email, or code. Accepted trade-off: confidence and familiarity lift are reported as aggregate group results, not matched pairs. Residual risk to manage in reporting: pre-survey respondents (invited) and post-survey respondents (attended) are not the same population, and the post group skews toward the more engaged, which can overstate lift. Mitigation: report n for each instrument, break results out by session date, and state the aggregate-not-matched limitation plainly in ESC materials. Anonymity was prioritized to protect candor on the blocker and acceptable-use questions.
A30: D10 | B30: Delivery platform - Zoom vs. Microsoft Teams | C30: Resolved 8/28 | D30: 2026-09-11 | E30: Resolved: sessions are delivered by Microsoft as Webinar in Teams under the Unified Contract, consistent with the Roll Out Plan. The webinar format was selected for capacity across the 5,606 E5 population and removes attendance-cap constraints. Attendance is captured from the Teams report.
A31: D11 | B31: Comms message distribution owner | C31: Resolved 8/27 | D31: 46269 | E31: Resolved: Comms distributes; Renee and Liz approve all launch messaging before send. Design remains with Vikki Pickett, message development with Tawanna and Atri. Tracked as a Phase 0 task with an approval workflow. Remaining item: agree an approval turnaround time, since session invites and survey pushes are date-driven and a slow approval loop delays the send rather than the drafting.
A32: D12 | B32: Copilot Basic reporting access route | C32: Open - critical | D32: 46269 | E32: Microsoft O365 reporting connection (preferred; no purchase, no training dependency) vs. licensing 50 users to activate Admin Center reporting (cost plus a Microsoft training requirement). Work with Microsoft is underway. Blocks all adoption metrics; must be settled before thresholds are locked at the 9/11 ESC.
A33: D13 | B33: HR Chatbot: Phase 3 Generalist roster from Dustin Hargis | C33: Resolved 9/15 | D33: 46280 | E33: Roughly 80 names needed to seat Cohort B in the 9/21-9/25 training window and to build the Phase 3 provisioning wave. Update 9/8: meeting scheduled with Dustin Hargis on 9/9, with Tawanna and Atri Manthani, to obtain the roster. Onboarding for Phase 3 is triggered by roster receipt, not a fixed date, so a late roster compresses training and access. Resolved 9/15/26: roster of approximately 80 Generalists obtained from Dustin Hargis.
A34: D14 | B34: HR Chatbot: security group naming and governance for post-phase access | C34: Folded into task | D34: 46290 | E34: Working name "HR Policy Chatbot - Testing Access", subject to City naming standards. Also confirm whether completed-phase testers retain access for remediation and retest or are removed, and whether licenses are reclaimed or reassigned after each phase sign-off. Still in progress as of 9/14/26. Pending a Microsoft call to walk through the setup, including reporting. Tawanna to follow up with Microsoft to schedule. Closed as a separate decision 9/15/26: the security group naming and governance question is carried entirely by the Microsoft review meeting task (Phase, HR Chatbot Readiness) and its dependent lines. Track it there.
A35: D15 | B35: HR Chatbot: license type and capacity for testing | C35: Folded into task | D35: 46290 | E35: Confirm with Microsoft and DC Faranak the license type required for chatbot testing, available capacity for 98 testers across three waves, and the validation step before each phase opens. Provisioning is phase-based and independent of training completion. Still in progress as of 9/14/26. Waiting on the same Microsoft call as D14 to walk through license type and capacity. Tawanna emailing Eli 9/14/26 to schedule. Closed as a separate decision 9/15/26: the license type and capacity question is carried entirely by the Microsoft review meeting task (Phase, HR Chatbot Readiness) and its dependent lines. Track it there.
A36: D16 | B36: HR Chatbot: whether a separate HIPAA determination is required for Copilot Studio and Dataverse | C36: Open | D36: 46304 | E36: Determined by the grounded content inventory. If the HR policy sources include employee health information, HIPAA coverage must be confirmed for the chatbot stack independently of the Copilot Basic agreements, and it becomes a hard gate before pilot deployment. Tawanna is confirming with Rajan Sharma.
A37: D17 | B37: Replacement host for session recordings and the Copilot Basic onboarding module (BizLibrary retiring) | C37: Resolved 9/15 | D37: 46280 | E37: BizLibrary is going away as the source for documents, so the recording, onboarding module and annual refresh lines in the plan no longer have a destination. Decide the replacement (SharePoint or the AI Teams site, Viva Learning, Stream, or the Resource Hub) before recording begins on 11/9, because the consent language on the session recording line names where recordings are stored and who can access them. Also confirm who owns the new-hire onboarding path in the replacement system, which connects to D5. Resolved 9/15/26: the Resource Hub replaces BizLibrary as the destination for the new-hire recording and the Do’s and Don’ts. Consent language on the session recording line should now name the Hub. Confirm Hub retention and access settings before recording begins 11/9.

Sheet Success Metrics
A1: Metric | B1: Source | C1: What It Shows | D1: Target / Threshold | E1: Reporting Frequency
A2: Active User Rate (Active/Enabled) | B2: Admin Center Usage report | C2: Whether licensed employees actually open the tool | D2: Training Reach: all six sessions delivered against the 5,606 E5 target. Active-user baseline established after Session 1. | E2: Weekly during rollout; monthly post-launch
A3: DAU / WAU | B3: Copilot Chat usage dashboard | C3: Whether usage is habitual, not one-time | D3: Habitual Use: 30% of users active at least three distinct days per week. Locked for ESC 9/4/26. | E3: Weekly
A4: Prompts per user | B4: Admin Center | C4: Depth of engagement | D4: Baseline after the first session, then track growth through the remaining sessions and beyond | E4: Monthly
A5: Week-over-week retention | B5: Copilot Dashboard | C5: Whether usage survives past the training spike | D5: Retention: 50% of new Copilot users return and use it again within 30 days. Locked for ESC 9/4/26. | E5: Weekly
A6: Agent adoption (Researcher/Analyst/Facilitator) | B6: Agent usage report | C6: Whether employees go beyond basic chat | D6: Track % of active users who have used a built-in agent at least once; grow steadily session over session | E6: Monthly
A7: Training completion / competency-check pass rate | B7: Viva Learning + Part 5 checklist | C7: Whether skills, not just access, were delivered | D7: 100% of trained employees either clear the five-item competency checklist or are flagged to their Champion for follow-up | E7: Per session
A8: Sessions delivered vs. target | B8: Training Capacity Plan tab | C8: Whether the rolling delivery schedule is on pace to reach ~7,407 employees within the planned window | D8: Six sessions delivered across 11/9-11/20 to ~5,606 E5 employees; on or ahead of the three-per-week cadence on the Training Capacity Plan tab. | E8: Weekly
A10: Note: Metric definitions were locked 9/4/26 ahead of the 9/11 ESC presentation and are reported against the same definitions every cycle. Sustained Use (50% of trained employees using Copilot weekly at 90 days) and Capability (confidence lift pre, post and at 90 days) are reported from the pulse survey cycle and the Copilot Dashboard together.

Sheet HR Chatbot Comms Calendar
A1: # | B1: Date | C1: Communication | D1: Audience | E1: Channel | F1: Owner
A2: C1 | B2: Sep. 4 | C2: Audit workflow validated; testing and audit process confirmed operational | D2: Project team, Leadership | E2: Email note | F2: Tawanna Armstrong-Ivory
A3: C2 | B3: Sep. 8 | C3: Microsoft review meeting agenda and materials | D3: Microsoft, project team | E3: Calendar invite plus agenda | F3: Tawanna Armstrong-Ivory
A4: C2a | B4: Sep. 11 | C4: ESC update: testing approach, communication plan, approval request | D4: ESC | E4: Meeting plus written summary | F4: Tawanna Armstrong-Ivory
A5: C3 | B5: Sep. 11, after ESC approval | C5: Supervisor notification: who is testing, which phase, time commitment | D5: Supervisors | E5: Email | F5: Tawanna Armstrong-Ivory
A6: C4 | B6: Sep. 11, after ESC approval | C6: Standardized tester onboarding email | D6: Phase 1 (15), Phase 2 (3) | E6: Email | F6: Tawanna Armstrong-Ivory
A7: C5 | B7: Sep. 11-12, after ESC approval | C7: Microsoft training session invitations with cohort assignment | D7: Phase 1, Phase 2, Phase 3 Cohort A | E7: Calendar invite | F7: Brian Umerley
A8: C6 | B8: On roster receipt, not before ESC approval | C8: Identical standardized onboarding email plus Cohort B training invitation | D8: Approximately 80 Generalists | E8: Email plus calendar invite | F8: Tawanna Armstrong-Ivory with Dustin Hargis
A9: C7 | B9: Sep. 14 | C9: Session 1 reminder and pre-read | D9: Phase 1 plus Phase 2 | E9: Email | F9: Brian Umerley
A10: C8 | B10: Sep. 16-18 | C10: Session 2 reminder and pre-read | D10: Phase 3 Cohort A | E10: Email | F10: Brian Umerley
A11: C9 | B11: Sep. 21-23 | C11: Session 3 reminder and pre-read | D11: Phase 3 Cohort B | E11: Email | F11: Brian Umerley
A12: C10 | B12: Sep. 18 and Sep. 25 | C12: Post-session follow-up: recording, materials, next steps, access separation restated | D12: Each session attendees | E12: Email | F12: Brian Umerley
... A53: C47 | B53: Before any production decision | C53: Production scope and financial planning readout | D53: AI Program, Leadership, ESC | E53: Meeting plus written summary | F53: Tawanna Armstrong-Ivory
